setup.cfg
setup.py
test/test.py
test/test_serializer.py
xwot/__init__.py
xwot/cmd.py
xwot/model.py
xwot/urn.py
xwot/compiler/__init__.py
xwot/compiler/backend/ExpressBackendBuilder.py
xwot/compiler/backend/FlaskBackendBuilder.py
xwot/compiler/backend/KleinBackendBuilder.py
xwot/compiler/backend/SinatraBackendBuilder.py
xwot/compiler/backend/__init__.py
xwot/compiler/backend/helper.py
xwot/compiler/frontend/__init__.py
xwot/compiler/frontend/node.py
xwot/compiler/frontend/parser.py
xwot/compiler/frontend/processing.py
xwot/compiler/frontend/visitor.py
xwot/device/__init__.py
xwot/device/door.py
xwot/device/lightbulb.py
xwot/device/shutter.py
xwot/device/waterdispenser.py
xwot/device/weatherstation.py
xwot/device/window.py
xwot/i2c/__init__.py
xwot/i2c/adapter.py
xwot/i2c/util.py
xwot/preprocessor/__init__.py
xwot/preprocessor/physical2virtual.py
xwot/util/SampleHardware.py
xwot/util/SubscriberDB.py
xwot/util/WebSocketSupport.py
xwot/util/__init__.py
xwot/util/annotator.py
xwot/util/apidocbuilder.py
xwot/util/flask.py
xwot/util/klein.py
xwot/util/vocab.py
xwot_py.egg-info/PKG-INFO
xwot_py.egg-info/SOURCES.txt
xwot_py.egg-info/dependency_links.txt
xwot_py.egg-info/entry_points.txt
xwot_py.egg-info/requires.txt
xwot_py.egg-info/top_level.txt