Metadata-Version: 1.1
Name: xwot-py
Version: 1.4.0
Summary: xwot
Home-page: UNKNOWN
Author: Alexander Rüedlinger
Author-email: a.rueedlinger@gmail.com
License: GPLv3
Platform: UNKNOWN
Classifier: License :: OSI Approved :: GNU General Public License v3 (GPLv3)
